s2shores/__init__.py
s2shores/bathy_physics.py
s2shores/waves_exceptions.py
s2shores/bathy_debug/__init__.py
s2shores/bathy_debug/display_utils.py
s2shores/bathy_debug/local_bathy_estimator_debug.py
s2shores/bathy_debug/polar_display.py
s2shores/bathy_debug/sinogram_display.py
s2shores/bathy_debug/spatial_correlation_bathy_estimator_debug.py
s2shores/bathy_debug/spatial_correlation_wave_fields_display.py
s2shores/bathy_debug/spatial_dft_bathy_estimator_debug.py
s2shores/bathy_debug/spatial_dft_wave_fields_display.py
s2shores/bathy_debug/temporal_correlation_bathy_estimator_debug.py
s2shores/bathy_debug/waves_image_display.py
s2shores/bathylauncher/__init__.py
s2shores/bathylauncher/bathy_launcher.py
s2shores/bathylauncher/bathy_processing.py
s2shores/bathylauncher/config/S2A_delta_times.csv
s2shores/bathylauncher/config/S2B_delta_times.csv
s2shores/bathylauncher/config/debug_area_example.yaml
s2shores/bathylauncher/config/debug_points_example.yaml
s2shores/bathylauncher/config/cnes/S2A_delta_times.csv
s2shores/bathylauncher/products/__init__.py
s2shores/bathylauncher/products/geotiff_product.py
s2shores/bathylauncher/products/s2_delta_time_provider.py
s2shores/bathylauncher/products/s2_image_product.py
s2shores/data_model/__init__.py
s2shores/data_model/bathymetry_sample_estimation.py
s2shores/data_model/bathymetry_sample_estimations.py
s2shores/data_model/bathymetry_sample_inversion.py
s2shores/data_model/estimated_bathy.py
s2shores/data_model/estimated_carto_bathy.py
s2shores/data_model/estimated_points_bathy.py
s2shores/data_model/wave_field_sample_dynamics.py
s2shores/data_model/wave_field_sample_estimation.py
s2shores/data_model/wave_field_sample_geometry.py
s2shores/data_providers/__init__.py
s2shores/data_providers/delta_time_provider.py
s2shores/data_providers/dis_to_shore_provider.py
s2shores/data_providers/gravity_provider.py
s2shores/data_providers/localized_data_provider.py
s2shores/data_providers/roi_provider.py
s2shores/generic_utils/__init__.py
truc-1.0.1.dist-info/licenses/AUTHORS.rst
truc-1.0.1.dist-info/licenses/LICENSE.txt
truc-1.0.1.dist-info/METADATA
truc-1.0.1.dist-info/WHEEL
truc-1.0.1.dist-info/entry_points.txt
truc-1.0.1.dist-info/top_level.txt
truc-1.0.1.dist-info/RECORD
